batocera_manager/__init__.py
batocera_manager/errors.py
batocera_manager/game.py
batocera_manager/system.py
batocera_manager/default_collections/__init__.py
batocera_manager/default_collections/batocera.py
batocera_manager/default_collections/const.py
batocera_manager-1.0.0.dist-info/LICENSE
batocera_manager-1.0.0.dist-info/METADATA
batocera_manager-1.0.0.dist-info/WHEEL
batocera_manager-1.0.0.dist-info/top_level.txt
batocera_manager-1.0.0.dist-info/RECORD
