Metadata-Version: 2.1
Name: batocera_manager
Version: 1.0.0
Summary: Control and monitor Batocera
Author-email: zhbjsh <zhbjsh@outlook.com>
Project-URL: Homepage, https://github.com/zhbjsh/batocera-manager
Project-URL: Bug Tracker, https://github.com/zhbjsh/batocera-manager/issues
Keywords: batocera,ssh,terminal,console,shell,bash,commands,command line
Classifier: Programming Language :: Python :: 3.10
Classifier: License :: OSI Approved :: MIT License
Classifier: Operating System :: OS Independent
Requires-Python: >=3.10
License-File: LICENSE
Requires-Dist: aiohttp >=3.8.5
Requires-Dist: ssh-terminal-manager >=1.0.3
